{
	"items": [
		{
			"values" : [
				   {
						"title": "Miniso",
						"url": "https://iprice.co.id/miniso/?utm_source=onsite&utm_medium=landing_page&utm_campaign=11_11_Sale",
						"img": "https://bilhasry-iprice.github.io/sale/data/id/image/miniso-sq.jpg"
				   },
				   {
				   		"title": "Samsung",
				   		"url" : "https://iprice.co.id/samsung/?utm_source=onsite&utm_medium=landing_page&utm_campaign=11_11_Sale",
				   		"img": "https://bilhasry-iprice.github.io/sale/data/id/image/samsung.jpg"
				   },
				   {
				   		"title": "Vincci",
				   		"url" : "https://iprice.co.id/vincci/?utm_source=onsite&utm_medium=landing_page&utm_campaign=11_11_Sale",
				   		"img": "https://bilhasry-iprice.github.io/sale/data/id/image/vincci.jpg"
				   },
				   {
				   		"title": "Adidas",
				   		"url" : "https://iprice.co.id/adidas/?utm_source=onsite&utm_medium=landing_page&utm_campaign=11_11_Sale",
				   		"img": "https://bilhasry-iprice.github.io/sale/data/id/image/adidas-sq.jpg"
				   },
				   {
				   		"title": "Fossil",
				   		"url" : "https://iprice.co.id/fossil/?utm_source=onsite&utm_medium=landing_page&utm_campaign=11_11_Sale",
				   		"img": "https://bilhasry-iprice.github.io/sale/data/id/image/fossil.jpg"
				   },
				   {
				   		"title": "Hush Puppies",
				   		"url" : "https://iprice.co.id/hush-puppies/?utm_source=onsite&utm_medium=landing_page&utm_campaign=11_11_Sale",
				   		"img": "https://bilhasry-iprice.github.io/sale/data/id/image/hushpuppies.jpg"
				   }
			]	
		}
 ]
}
