{
 "products" : [
 	{
		"title": "Something Borrowed",
		"description" : "Something Borrowed",
		"url": "http://bit.ly/2hToNFX",
		"img": "image/Something_borrowed_banner.png"
	},
	{
		"title": "Nike",
		"description" : "Nike",
		"url": "http://bit.ly/2yfANaE",
		"img": "image/Nike_banner.png"
	},
	{
		"title": "Mango",
		"description" : "Mango",
		"url": "http://bit.ly/2hRvpV1",
		"img": "image/Mango_banner.png"
	}
],
 "top_brands": [
	   {
			"title": "Swatch",
			"url": "https://iprice.ph/swatch/?utm_source=onsite&utm_medium=landing_page&utm_campaign=11_11_Sale",
			"img": "image/swatch-sq.jpg"
	   },
	   {
	   		"title": "Samsung",
	   		"url" : "https://iprice.ph/samsung/?utm_source=onsite&utm_medium=landing_page&utm_campaign=11_11_Sale",
	   		"img": "image/samsung.jpg"
	   },
	   {
	   		"title": "Forever 21",
	   		"url" : "https://iprice.ph/forever-21/?utm_source=onsite&utm_medium=landing_page&utm_campaign=11_11_Sale",
	   		"img": "image/forever21-sq.jpg"
	   },
	   {
	   		"title": "Herschel",
	   		"url" : "https://iprice.ph/herschel-supply-co/?utm_source=onsite&utm_medium=landing_page&utm_campaign=11_11_Sale",
	   		"img": "image/herschel-sq.jpg"
	   },
	   {
	   		"title": "Vans",
	   		"url" : "https://iprice.ph/vans/?utm_source=onsite&utm_medium=landing_page&utm_campaign=11_11_Sale",
	   		"img": "image/vans-sq.jpg"
	   },
	   {
	   		"title": "Nike",
	   		"url" : "https://iprice.ph/nike/?utm_source=onsite&utm_medium=landing_page&utm_campaign=11_11_Sale",
	   		"img": "image/nike-sq.jpg"
	   }
	],
 "brands": [
        {
            "title": "Zalora",
            "description": "11.11 Singles Day Your Way. Up to 50% Off",
            "url": "http://bit.ly/2hbTcSx",
            "img": "image/zalora_square_50.jpg",
            "cta" : "Shop Now"
        },
        {
            "title": "Uber",
            "description": "For no reason being late again",
            "url": "https://iprice.ph/coupons/uber/?utm_source=onsite&utm_medium=landing_page&utm_campaign=11_11_Sale",
            "img": "image/Uber_box_banner.jpg",
            "cta" : "Shop Now"
        },
        {
            "title": "Lazada",
            "description": "Biggest Sale in The Universe",
            "url": "http://bit.ly/2hdasn2",
            "img": "image/lazada_square.jpg"
        },
        {
            "title": "YesStyles",
            "description": "Happy Singles' Day",
            "url": "http://bit.ly/2j93NhQ",
            "img": "image/Yesstyles_banner.jpg",
            "cta" : "Shop Now"
        }
    ],
 "coupons": [
   {
		"title": "Zalora",
		"highlight" : "13% OFF",
		"coupon_code" : "A11FORYOU",
		"description" : "Take 13% off sitewide with min. spend P1,750",
		"url": "https://iprice.ph/coupons/zalora/?_id=aacff17c3508a8395e6dc403d554aa4d8bbb1072&position=1&sub_product=coupon-store&_exit=%2Fcoupons%2Fzalora%2F",
		"img": "image/zalora.jpg",
		"type" : "popup"
   },
   {
		"title": "Zalora",
		"highlight" : "70% OFF",
		"coupon_code" : "DG20",
		"description" : "Dolce & Gabanna product up to 70% OFF + extra 20% OFF",
		"url": "https://iprice.ph/coupons/zalora/?_id=f003cf0902746a4fdf9e4da8972d667684e6ecea&position=5&sub_product=coupon-store&_exit=%2Fcoupons%2Fzalora%2F",
		"img": "image/zalora.jpg",
		"type" : "popup"
   },
   {
		"title": "Lazada",
		"highlight" : "Up to 30% OFF",
		"coupon_code" : "UNILVR",
		"description" : "Unilever Exclusive Sale - Up to 30% off with code for Dove, Ponds, TRESemme, St. Ives & more",
		"url": "https://iprice.ph/coupons/lazada/?_id=e063bc220b5264175132c0db2fbe27884ba2c003&position=11&sub_product=coupon-store&_exit=%2Fcoupons%2Flazada%2F",
		"img": "image/lazada.jpg",
		"type" : "popup"
   },
   {
		"title": "Lazada",
		"highlight" : "P100 OFF",
		"coupon_code" : "COLGATEPALMOLIVE100",
		"description" : "Save P100 with Colgate",
		"url": "https://iprice.ph/coupons/lazada/?_id=62335efbcca66c915ff1cdc9e6be79b2a70c9f6e&position=12&sub_product=coupon-store&_exit=%2Fcoupons%2Flazada%2F%3F_id%3De063bc220b5264175132c0db2fbe27884ba2c003%26position%3D11%26sub_product%3Dcoupon-store%26_exit%3D%252Fcoupons%252Flazada%252F",
		"img": "image/lazada.jpg",
		"type" : "popup"
   },
   {
		"title": "Lazada",
		"highlight" : "P100 OFF",
		"coupon_code" : "DUREX100",
		"description" : "Durex Voucher - Take P100 off with Code",
		"url": "https://iprice.ph/coupons/lazada/?_id=bfe6434b2448e54fd984e08ac5d5b5ba6d0fa989&position=14&sub_product=coupon-store&_exit=%2Fcoupons%2Flazada%2F%3F_id%3Dbfe6434b2448e54fd984e08ac5d5b5ba6d0fa989%26position%3D14%26sub_product%3Dcoupon-store%26_exit%3D%252Fcoupons%252Flazada%252F%253F_id%253D0a9757f49beb893daf11631b5bc79c18934bc8d3%2526position%253D13%2526sub_product%253Dcoupon-store%2526_exit%253D%25252Fcoupons%25252Flazada%25252F%25253F_id%25253D62335efbcca66c915ff1cdc9e6be79b2a70c9f6e%252526position%25253D12%252526sub_product%25253Dcoupon-store%252526_exit%25253D%2525252Fcoupons%2525252Flazada%2525252F%2525253F_id%2525253De063bc220b5264175132c0db2fbe27884ba2c003%25252526position%2525253D11%25252526sub_product%2525253Dcoupon-store%25252526_exit%2525253D%252525252Fcoupons%252525252Flazada%252525252F",
		"img": "image/lazada.jpg",
		"type" : "popup"
   },
   {
		"title": "Lazada",
		"highlight" : "P500 OFF",
		"coupon_code" : "LENOVO100",
		"description" : "P500 OFF on First 250 LENOVO Customers",
		"url": "https://iprice.ph/coupons/lazada/?_id=fbdb6c10dbbbf2195c0f207c7d01126201f7a171&position=16&sub_product=coupon-store&_exit=%2Fcoupons%2Flazada%2F",
		"img": "image/lazada.jpg",
		"type" : "popup"
   },
   {
		"title": "Lazada",
		"highlight" : "P150 OFF",
		"coupon_code" : "RAPPLER150",
		"description" : "P150 OFF for New Customers | Min. Purchase of P1,000",
		"url": "https://iprice.ph/coupons/lazada/?_id=69bfd19937cfd831753e89dca403280c5f1db168&position=4&sub_product=coupon-store&_exit=%2Fcoupons%2Flazada%2F%3F_id%3Dfbdb6c10dbbbf2195c0f207c7d01126201f7a171%26position%3D16%26sub_product%3Dcoupon-store%26_exit%3D%252Fcoupons%252Flazada%252F%253F_id%253Dfbdb6c10dbbbf2195c0f207c7d01126201f7a171%2526position%253D16%2526sub_product%253Dcoupon-store%2526_exit%253D%25252Fcoupons%25252Flazada%25252F",
		"img": "image/lazada.jpg",
		"type" : "popup"
   },
   {
		"title": "Lazada",
		"highlight" : "12% OFF",
		"coupon_code" : "LOVE2CLICK12",
		"description" : "12% Off for Citi Bank Credit Card Users with Min. Purchase of P2,000",
		"url": "https://iprice.ph/coupons/lazada/?_id=6ef8381372df8e5363c799b53def0d65accfe922&position=18&sub_product=coupon-store&_exit=%2Fcoupons%2Flazada%2F%3F_id%3D69bfd19937cfd831753e89dca403280c5f1db168%26position%3D4%26sub_product%3Dcoupon-store%26_exit%3D%252Fcoupons%252Flazada%252F%253F_id%253Dfbdb6c10dbbbf2195c0f207c7d01126201f7a171%2526position%253D16%2526sub_product%253Dcoupon-store%2526_exit%253D%25252Fcoupons%25252Flazada%25252F%25253F_id%25253Dfbdb6c10dbbbf2195c0f207c7d01126201f7a171%252526position%25253D16%252526sub_product%25253Dcoupon-store%252526_exit%25253D%2525252Fcoupons%2525252Flazada%2525252F",
		"img": "image/lazada.jpg",
		"type" : "popup"
   },
   {
		"title": "Lazada",
		"highlight" : "Up to 75% OFF",
		"coupon_code" : "RAPPLER11OR",
		"description" : "75% + 11% OFF with Exclusive Code | Min. Spend P1,000 for New Customers",
		"url": "https://iprice.ph/coupons/lazada/?_id=45762519c02896bdbb7812c220917f1035dd169d&position=6&sub_product=coupon-store&_exit=%2Fcoupons%2Flazada%2F%3F_id%3D6ef8381372df8e5363c799b53def0d65accfe922%26position%3D18%26sub_product%3Dcoupon-store%26_exit%3D%252Fcoupons%252Flazada%252F%253F_id%253D69bfd19937cfd831753e89dca403280c5f1db168%2526position%253D4%2526sub_product%253Dcoupon-store%2526_exit%253D%25252Fcoupons%25252Flazada%25252F%25253F_id%25253Dfbdb6c10dbbbf2195c0f207c7d01126201f7a171%252526position%25253D16%252526sub_product%25253Dcoupon-store%252526_exit%25253D%2525252Fcoupons%2525252Flazada%2525252F%2525253F_id%2525253Dfbdb6c10dbbbf2195c0f207c7d01126201f7a171%25252526position%2525253D16%25252526sub_product%2525253Dcoupon-store%25252526_exit%2525253D%252525252Fcoupons%252525252Flazada%252525252F",
		"img": "image/lazada.jpg",
		"type" : "popup"
   },
   {
		"title": "Lazada",
		"highlight" : "12% OFF",
		"coupon_code" : "LZDORTAOBAO",
		"description" : "Taobao Happy 11.11 Voucher Code - 12% Off with min spend of P1,000",
		"url": "https://iprice.ph/coupons/lazada/?_id=56c99d082d6b6c3a79f9293452ac7c8dd9db9696&position=20&sub_product=coupon-store&_exit=%2Fcoupons%2Flazada%2F%3F_id%3D45762519c02896bdbb7812c220917f1035dd169d%26position%3D6%26sub_product%3Dcoupon-store%26_exit%3D%252Fcoupons%252Flazada%252F%253F_id%253D6ef8381372df8e5363c799b53def0d65accfe922%2526position%253D18%2526sub_product%253Dcoupon-store%2526_exit%253D%25252Fcoupons%25252Flazada%25252F%25253F_id%25253D69bfd19937cfd831753e89dca403280c5f1db168%252526position%25253D4%252526sub_product%25253Dcoupon-store%252526_exit%25253D%2525252Fcoupons%2525252Flazada%2525252F%2525253F_id%2525253Dfbdb6c10dbbbf2195c0f207c7d01126201f7a171%25252526position%2525253D16%25252526sub_product%2525253Dcoupon-store%25252526_exit%2525253D%252525252Fcoupons%252525252Flazada%252525252F%252525253F_id%252525253Dfbdb6c10dbbbf2195c0f207c7d01126201f7a171%2525252526position%252525253D16%2525252526sub_product%252525253Dcoupon-store%2525252526_exit%252525253D%25252525252Fcoupons%25252525252Flazada%25252525252F",
		"img": "image/lazada.jpg",
		"type" : "popup"
   },
   {
		"title": "Lazada",
		"highlight" : "P150 OFF",
		"coupon_code" : "LZDNCTAOBAO",
		"description" : "Taobao Happy 11.11 Voucher Code - P150 Off for New Customers | Min. Spend of P1,000",
		"url": "https://iprice.ph/coupons/lazada/?_id=8ec7ff0ec92e94d175aa717600979ab74f9c1796&position=21&sub_product=coupon-store&_exit=%2Fcoupons%2Flazada%2F%3F_id%3D8ec7ff0ec92e94d175aa717600979ab74f9c1796%26position%3D21%26sub_product%3Dcoupon-store%26_exit%3D%252Fcoupons%252Flazada%252F%253F_id%253D56c99d082d6b6c3a79f9293452ac7c8dd9db9696%2526position%253D20%2526sub_product%253Dcoupon-store%2526_exit%253D%25252Fcoupons%25252Flazada%25252F%25253F_id%25253D45762519c02896bdbb7812c220917f1035dd169d%252526position%25253D6%252526sub_product%25253Dcoupon-store%252526_exit%25253D%2525252Fcoupons%2525252Flazada%2525252F%2525253F_id%2525253D6ef8381372df8e5363c799b53def0d65accfe922%25252526position%2525253D18%25252526sub_product%2525253Dcoupon-store%25252526_exit%2525253D%252525252Fcoupons%252525252Flazada%252525252F%252525253F_id%252525253D69bfd19937cfd831753e89dca403280c5f1db168%2525252526position%252525253D4%2525252526sub_product%252525253Dcoupon-store%2525252526_exit%252525253D%25252525252Fcoupons%25252525252Flazada%25252525252F%25252525253F_id%25252525253Dfbdb6c10dbbbf2195c0f207c7d01126201f7a171%252525252526position%25252525253D16%252525252526sub_product%25252525253Dcoupon-store%252525252526_exit%25252525253D%2525252525252Fcoupons%2525252525252Flazada%2525252525252F%2525252525253F_id%2525252525253Dfbdb6c10dbbbf2195c0f207c7d01126201f7a171%25252525252526position%2525252525253D16%25252525252526sub_product%2525252525253Dcoupon-store%25252525252526_exit%2525252525253D%252525252525252Fcoupons%252525252525252Flazada%252525252525252F",
		"img": "image/lazada.jpg",
		"type" : "popup"
   },
   {
		"title": "Lazada",
		"highlight" : "10% OFF",
		"coupon_code" : "LAZOR10NOV",
		"description" : "Get 10% off when you spend P1,000",
		"url": "https://iprice.ph/coupons/lazada/?_id=e74c2f174cf4422256ee9d33238be04afdba8d06&position=22&sub_product=coupon-store&_exit=%2Fcoupons%2Flazada%2F%3F_id%3D8ec7ff0ec92e94d175aa717600979ab74f9c1796%26position%3D21%26sub_product%3Dcoupon-store%26_exit%3D%252Fcoupons%252Flazada%252F%253F_id%253D8ec7ff0ec92e94d175aa717600979ab74f9c1796%2526position%253D21%2526sub_product%253Dcoupon-store%2526_exit%253D%25252Fcoupons%25252Flazada%25252F%25253F_id%25253D56c99d082d6b6c3a79f9293452ac7c8dd9db9696%252526position%25253D20%252526sub_product%25253Dcoupon-store%252526_exit%25253D%2525252Fcoupons%2525252Flazada%2525252F%2525253F_id%2525253D45762519c02896bdbb7812c220917f1035dd169d%25252526position%2525253D6%25252526sub_product%2525253Dcoupon-store%25252526_exit%2525253D%252525252Fcoupons%252525252Flazada%252525252F%252525253F_id%252525253D6ef8381372df8e5363c799b53def0d65accfe922%2525252526position%252525253D18%2525252526sub_product%252525253Dcoupon-store%2525252526_exit%252525253D%25252525252Fcoupons%25252525252Flazada%25252525252F%25252525253F_id%25252525253D69bfd19937cfd831753e89dca403280c5f1db168%252525252526position%25252525253D4%252525252526sub_product%25252525253Dcoupon-store%252525252526_exit%25252525253D%2525252525252Fcoupons%2525252525252Flazada%2525252525252F%2525252525253F_id%2525252525253Dfbdb6c10dbbbf2195c0f207c7d01126201f7a171%25252525252526position%2525252525253D16%25252525252526sub_product%2525252525253Dcoupon-store%25252525252526_exit%2525252525253D%252525252525252Fcoupons%252525252525252Flazada%252525252525252F%252525252525253F_id%252525252525253Dfbdb6c10dbbbf2195c0f207c7d01126201f7a171%2525252525252526position%252525252525253D16%2525252525252526sub_product%252525252525253Dcoupon-store%2525252525252526_exit%252525252525253D%25252525252525252Fcoupons%25252525252525252Flazada%25252525252525252F",
		"img": "image/lazada.jpg",
		"type" : "popup"
   },
   {
		"title": "Lazada",
		"highlight" : "P500 OFF",
		"coupon_code" : "PAMPERS500",
		"description" : "Pampers Diapers Code - Enjoy P500 OFF for first 500 customers | Min. spend of P2,500",
		"url": "https://iprice.ph/coupons/lazada/?_id=04736bcd13ff87c850ec2d989ad537aa9e5271fa&position=18&sub_product=coupon-store&_exit=%2Fcoupons%2Flazada%2F%3F_id%3De74c2f174cf4422256ee9d33238be04afdba8d06%26position%3D22%26sub_product%3Dcoupon-store%26_exit%3D%252Fcoupons%252Flazada%252F%253F_id%253D8ec7ff0ec92e94d175aa717600979ab74f9c1796%2526position%253D21%2526sub_product%253Dcoupon-store%2526_exit%253D%25252Fcoupons%25252Flazada%25252F%25253F_id%25253D8ec7ff0ec92e94d175aa717600979ab74f9c1796%252526position%25253D21%252526sub_product%25253Dcoupon-store%252526_exit%25253D%2525252Fcoupons%2525252Flazada%2525252F%2525253F_id%2525253D56c99d082d6b6c3a79f9293452ac7c8dd9db9696%25252526position%2525253D20%25252526sub_product%2525253Dcoupon-store%25252526_exit%2525253D%252525252Fcoupons%252525252Flazada%252525252F%252525253F_id%252525253D45762519c02896bdbb7812c220917f1035dd169d%2525252526position%252525253D6%2525252526sub_product%252525253Dcoupon-store%2525252526_exit%252525253D%25252525252Fcoupons%25252525252Flazada%25252525252F%25252525253F_id%25252525253D6ef8381372df8e5363c799b53def0d65accfe922%252525252526position%25252525253D18%252525252526sub_product%25252525253Dcoupon-store%252525252526_exit%25252525253D%2525252525252Fcoupons%2525252525252Flazada%2525252525252F%2525252525253F_id%2525252525253D69bfd19937cfd831753e89dca403280c5f1db168%25252525252526position%2525252525253D4%25252525252526sub_product%2525252525253Dcoupon-store%25252525252526_exit%2525252525253D%252525252525252Fcoupons%252525252525252Flazada%252525252525252F%252525252525253F_id%252525252525253Dfbdb6c10dbbbf2195c0f207c7d01126201f7a171%2525252525252526position%252525252525253D16%2525252525252526sub_product%252525252525253Dcoupon-store%2525252525252526_exit%252525252525253D%25252525252525252Fcoupons%25252525252525252Flazada%25252525252525252F%25252525252525253F_id%25252525252525253Dfbdb6c10dbbbf2195c0f207c7d01126201f7a171%252525252525252526position%25252525252525253D16%252525252525252526sub_product%25252525252525253Dcoupon-store%252525252525252526_exit%25252525252525253D%2525252525252525252Fcoupons%2525252525252525252Flazada%2525252525252525252F",
		"img": "image/lazada.jpg",
		"type" : "popup"
   },
   {
		"title": "Lazada",
		"highlight" : "20% OFF",
		"coupon_code" : "UNILVR",
		"description" : "Tresemme Voucher Code - 20% OFF",
		"url": "https://iprice.ph/coupons/lazada/?_id=2f1e1613599ef1974bec6fa0e019374781eb177d&position=17&sub_product=coupon-store&_exit=%2Fcoupons%2Flazada%2F%3F_id%3D04736bcd13ff87c850ec2d989ad537aa9e5271fa%26position%3D18%26sub_product%3Dcoupon-store%26_exit%3D%252Fcoupons%252Flazada%252F%253F_id%253De74c2f174cf4422256ee9d33238be04afdba8d06%2526position%253D22%2526sub_product%253Dcoupon-store%2526_exit%253D%25252Fcoupons%25252Flazada%25252F%25253F_id%25253D8ec7ff0ec92e94d175aa717600979ab74f9c1796%252526position%25253D21%252526sub_product%25253Dcoupon-store%252526_exit%25253D%2525252Fcoupons%2525252Flazada%2525252F%2525253F_id%2525253D8ec7ff0ec92e94d175aa717600979ab74f9c1796%25252526position%2525253D21%25252526sub_product%2525253Dcoupon-store%25252526_exit%2525253D%252525252Fcoupons%252525252Flazada%252525252F%252525253F_id%252525253D56c99d082d6b6c3a79f9293452ac7c8dd9db9696%2525252526position%252525253D20%2525252526sub_product%252525253Dcoupon-store%2525252526_exit%252525253D%25252525252Fcoupons%25252525252Flazada%25252525252F%25252525253F_id%25252525253D45762519c02896bdbb7812c220917f1035dd169d%252525252526position%25252525253D6%252525252526sub_product%25252525253Dcoupon-store%252525252526_exit%25252525253D%2525252525252Fcoupons%2525252525252Flazada%2525252525252F%2525252525253F_id%2525252525253D6ef8381372df8e5363c799b53def0d65accfe922%25252525252526position%2525252525253D18%25252525252526sub_product%2525252525253Dcoupon-store%25252525252526_exit%2525252525253D%252525252525252Fcoupons%252525252525252Flazada%252525252525252F%252525252525253F_id%252525252525253D69bfd19937cfd831753e89dca403280c5f1db168%2525252525252526position%252525252525253D4%2525252525252526sub_product%252525252525253Dcoupon-store%2525252525252526_exit%252525252525253D%25252525252525252Fcoupons%25252525252525252Flazada%25252525252525252F%25252525252525253F_id%25252525252525253Dfbdb6c10dbbbf2195c0f207c7d01126201f7a171%252525252525252526position%25252525252525253D16%252525252525252526sub_product%25252525252525253Dcoupon-store%252525252525252526_exit%25252525252525253D%2525252525252525252Fcoupons%2525252525252525252Flazada%2525252525252525252F%2525252525252525253F_id%2525252525252525253Dfbdb6c10dbbbf2195c0f207c7d01126201f7a171%25252525252525252526position%2525252525252525253D16%25252525252525252526sub_product%2525252525252525253Dcoupon-store%25252525252525252526_exit%2525252525252525253D%252525252525252525252Fcoupons%252525252525252525252Flazada%252525252525252525252F",
		"img": "image/lazada.jpg",
		"type" : "popup"
   },
   {
		"title": "Lazada",
		"highlight" : "P100 OFF",
		"coupon_code" : "WATSONS100",
		"description" : "P100 off on Veet Hair Removal",
		"url": "https://iprice.ph/coupons/lazada/?_id=ca46db89f7842fbf44660245392d7f1440d3c584&position=16&sub_product=coupon-store&_exit=%2Fcoupons%2Flazada%2F%3F_id%3D589e88e27a439bb5fcc9ae6ea6216e186431a8ee%26position%3D15%26sub_product%3Dcoupon-store%26_exit%3D%252Fcoupons%252Flazada%252F%253F_id%253D2f1e1613599ef1974bec6fa0e019374781eb177d%2526position%253D17%2526sub_product%253Dcoupon-store%2526_exit%253D%25252Fcoupons%25252Flazada%25252F%25253F_id%25253D2f1e1613599ef1974bec6fa0e019374781eb177d%252526position%25253D17%252526sub_product%25253Dcoupon-store%252526_exit%25253D%2525252Fcoupons%2525252Flazada%2525252F%2525253F_id%2525253D04736bcd13ff87c850ec2d989ad537aa9e5271fa%25252526position%2525253D18%25252526sub_product%2525253Dcoupon-store%25252526_exit%2525253D%252525252Fcoupons%252525252Flazada%252525252F%252525253F_id%252525253De74c2f174cf4422256ee9d33238be04afdba8d06%2525252526position%252525253D22%2525252526sub_product%252525253Dcoupon-store%2525252526_exit%252525253D%25252525252Fcoupons%25252525252Flazada%25252525252F%25252525253F_id%25252525253D8ec7ff0ec92e94d175aa717600979ab74f9c1796%252525252526position%25252525253D21%252525252526sub_product%25252525253Dcoupon-store%252525252526_exit%25252525253D%2525252525252Fcoupons%2525252525252Flazada%2525252525252F%2525252525253F_id%2525252525253D8ec7ff0ec92e94d175aa717600979ab74f9c1796%25252525252526position%2525252525253D21%25252525252526sub_product%2525252525253Dcoupon-store%25252525252526_exit%2525252525253D%252525252525252Fcoupons%252525252525252Flazada%252525252525252F%252525252525253F_id%252525252525253D56c99d082d6b6c3a79f9293452ac7c8dd9db9696%2525252525252526position%252525252525253D20%2525252525252526sub_product%252525252525253Dcoupon-store%2525252525252526_exit%252525252525253D%25252525252525252Fcoupons%25252525252525252Flazada%25252525252525252F%25252525252525253F_id%25252525252525253D45762519c02896bdbb7812c220917f1035dd169d%252525252525252526position%25252525252525253D6%252525252525252526sub_product%25252525252525253Dcoupon-store%252525252525252526_exit%25252525252525253D%2525252525252525252Fcoupons%2525252525252525252Flazada%2525252525252525252F%2525252525252525253F_id%2525252525252525253D6ef8381372df8e5363c799b53def0d65accfe922%25252525252525252526position%2525252525252525253D18%25252525252525252526sub_product%2525252525252525253Dcoupon-store%25252525252525252526_exit%2525252525252525253D%252525252525252525252Fcoupons%252525252525252525252Flazada%252525252525252525252F%252525252525252525253F_id%252525252525252525253D69bfd19937cfd831753e89dca403280c5f1db168%2525252525252525252526position%252525252525252525253D4%2525252525252525252526sub_product%252525252525252525253Dcoupon-store%2525252525252525252526_exit%252525252525252525253D%25252525252525252525252Fcoupons%25252525252525252525252Flazada%25252525252525252525252F%25252525252525252525253F_id%25252525252525252525253Dfbdb6c10dbbbf2195c0f207c7d01126201f7a171%252525252525252525252526position%25252525252525252525253D16%252525252525252525252526sub_product%25252525252525252525253Dcoupon-store%252525252525252525252526_exit%25252525252525252525253D%2525252525252525252525252Fcoupons%2525252525252525252525252Flazada%2525252525252525252525252F%2525252525252525252525253F_id%2525252525252525252525253Dfbdb6c10dbbbf2195c0f207c7d01126201f7a171%25252525252525252525252526position%2525252525252525252525253D16%25252525252525252525252526sub_product%2525252525252525252525253Dcoupon-store%25252525252525252525252526_exit%2525252525252525252525253D%252525252525252525252525252Fcoupons%252525252525252525252525252Flazada%252525252525252525252525252F",
		"img": "image/lazada.jpg",
		"type" : "popup"
   },
   {
		"title": "Lazada",
		"highlight" : "P500 OFF",
		"coupon_code" : "OLAY200",
		"description" : "Olay Promo Code - P500 off for first 500 customers | Min. purchase of P2,500",
		"url": "https://iprice.ph/coupons/lazada/?_id=589e88e27a439bb5fcc9ae6ea6216e186431a8ee&position=15&sub_product=coupon-store&_exit=%2Fcoupons%2Flazada%2F%3F_id%3D2f1e1613599ef1974bec6fa0e019374781eb177d%26position%3D17%26sub_product%3Dcoupon-store%26_exit%3D%252Fcoupons%252Flazada%252F%253F_id%253D2f1e1613599ef1974bec6fa0e019374781eb177d%2526position%253D17%2526sub_product%253Dcoupon-store%2526_exit%253D%25252Fcoupons%25252Flazada%25252F%25253F_id%25253D04736bcd13ff87c850ec2d989ad537aa9e5271fa%252526position%25253D18%252526sub_product%25253Dcoupon-store%252526_exit%25253D%2525252Fcoupons%2525252Flazada%2525252F%2525253F_id%2525253De74c2f174cf4422256ee9d33238be04afdba8d06%25252526position%2525253D22%25252526sub_product%2525253Dcoupon-store%25252526_exit%2525253D%252525252Fcoupons%252525252Flazada%252525252F%252525253F_id%252525253D8ec7ff0ec92e94d175aa717600979ab74f9c1796%2525252526position%252525253D21%2525252526sub_product%252525253Dcoupon-store%2525252526_exit%252525253D%25252525252Fcoupons%25252525252Flazada%25252525252F%25252525253F_id%25252525253D8ec7ff0ec92e94d175aa717600979ab74f9c1796%252525252526position%25252525253D21%252525252526sub_product%25252525253Dcoupon-store%252525252526_exit%25252525253D%2525252525252Fcoupons%2525252525252Flazada%2525252525252F%2525252525253F_id%2525252525253D56c99d082d6b6c3a79f9293452ac7c8dd9db9696%25252525252526position%2525252525253D20%25252525252526sub_product%2525252525253Dcoupon-store%25252525252526_exit%2525252525253D%252525252525252Fcoupons%252525252525252Flazada%252525252525252F%252525252525253F_id%252525252525253D45762519c02896bdbb7812c220917f1035dd169d%2525252525252526position%252525252525253D6%2525252525252526sub_product%252525252525253Dcoupon-store%2525252525252526_exit%252525252525253D%25252525252525252Fcoupons%25252525252525252Flazada%25252525252525252F%25252525252525253F_id%25252525252525253D6ef8381372df8e5363c799b53def0d65accfe922%252525252525252526position%25252525252525253D18%252525252525252526sub_product%25252525252525253Dcoupon-store%252525252525252526_exit%25252525252525253D%2525252525252525252Fcoupons%2525252525252525252Flazada%2525252525252525252F%2525252525252525253F_id%2525252525252525253D69bfd19937cfd831753e89dca403280c5f1db168%25252525252525252526position%2525252525252525253D4%25252525252525252526sub_product%2525252525252525253Dcoupon-store%25252525252525252526_exit%2525252525252525253D%252525252525252525252Fcoupons%252525252525252525252Flazada%252525252525252525252F%252525252525252525253F_id%252525252525252525253Dfbdb6c10dbbbf2195c0f207c7d01126201f7a171%2525252525252525252526position%252525252525252525253D16%2525252525252525252526sub_product%252525252525252525253Dcoupon-store%2525252525252525252526_exit%252525252525252525253D%25252525252525252525252Fcoupons%25252525252525252525252Flazada%25252525252525252525252F%25252525252525252525253F_id%25252525252525252525253Dfbdb6c10dbbbf2195c0f207c7d01126201f7a171%252525252525252525252526position%25252525252525252525253D16%252525252525252525252526sub_product%25252525252525252525253Dcoupon-store%252525252525252525252526_exit%25252525252525252525253D%2525252525252525252525252Fcoupons%2525252525252525252525252Flazada%2525252525252525252525252F",
		"img": "image/lazada.jpg",
		"type" : "popup"
   },
   {
		"title": "Hotels.com",
		"highlight" : "5% OFF",
		"coupon_code" : "PH5OFF",
		"description" : "Get 5% OFF on top of hotel deals",
		"url": "https://iprice.ph/coupons/hotelscom/?_id=e99790b4a5c03276e71c0e95f0032b33f3309c60&position=1&sub_product=coupon-store&_exit=%2Fcoupons%2Fhotelscom%2F",
		"img": "image/hotelscom.jpg",
		"type" : "popup"
   },
   {
		"title": "Expedia",
		"highlight" : "10% OFF",
		"coupon_code" : "required",
		"description" : "Get extra 10% OFF for BDO customers",
		"url": "https://iprice.ph/coupons/expedia/?_id=2073e8db6f14f21b70a9c217421f7df23bade037&position=1&sub_product=coupon-store&_exit=%2Fcoupons%2Fexpedia%2F",
		"img": "image/expedia.jpg",
		"type" : "direct"
   },
   {
		"title": "KKday",
		"highlight" : "10% OFF",
		"coupon_code" : "CITISG10",
		"description" : "Extra 10% OFF at Taiwan with Citibank",
		"url": "https://iprice.ph/coupons/kkday/?_id=f1a6de115ca64e902f8b0294553bacc049fc8c1c&position=2&sub_product=coupon-store&_exit=%2Fcoupons%2Fkkday%2F",
		"img": "image/kkday.jpg",
		"type" : "popup"
   },
   {
		"title": "Agoda",
		"highlight" : "60% OFF",
		"coupon_code" : "required",
		"description" : "Save 60% OFF on your trip with Agoda",
		"url": "https://iprice.ph/r/c/?_id=3b22f415c876fd82f2e1bc4b71aa87f9079009fe&position=1&sub_product=coupon-store&_exit=%2Fcoupons%2Fagoda%2F",
		"img": "image/agoda.jpg",
		"type" : "direct"
   },
   {
		"title": "Sephora",
		"highlight" : "Free Gift",
		"coupon_code" : "MATTEROUGE",
		"description" : "FREE Sephora rouge matte lipstick with ANY lip products",
		"url": "https://iprice.ph/coupons/sephora/?_id=4c53c08a5bc96a8765e4a8f6b657b2e98bb970ac&position=6&sub_product=coupon-store&_exit=%2Fcoupons%2Fsephora%2F",
		"img": "image/sephora.jpg",
		"type" : "popup"
   },
   {
		"title": "Althea",
		"highlight" : "10% OFF",
		"coupon_code" : "*****",
		"description" : "10% OFF sitewide with any purchase",
		"url": "https://iprice.ph/coupons/althea/?_id=bdfeece440b308ec35d7a447cfeb86793b30a3e7&position=4&sub_product=coupon-store&_exit=%2Fcoupons%2Falthea%2F",
		"img": "image/althea.jpg",
		"type" : "popup"
   },
   {
		"title": "Lazada",
		"highlight" : "12% OFF",
		"coupon_code" : "page",
		"description" : "Get up to 12% OFF your favourite stores",
		"url": "https://iprice.ph/coupons/lazada/?_id=f2410f7a9791679fa67b64d24affd4dcaf159373&position=3&sub_product=coupon-store&_exit=%2Fcoupons%2Flazada%2F",
		"img": "image/lazada.jpg",
		"type" : "popup"
   },
   {
		"title": "Grab",
		"highlight" : "P15 OFF",
		"coupon_code" : "PANAGBENGA",
		"description" : "P15 OFF x 5 rides",
		"url": "https://iprice.ph/coupons/grab/?_id=e28e0808ae68f589612eaf8cd7c8df9541f5cd2b&position=5&sub_product=coupon-store&_exit=%2Fcoupons%2Fgrab%2F",
		"img": "image/grab.jpg",
		"type" : "popup"
   },
   {
		"title": "Uber",
		"highlight" : "P60 OFF",
		"coupon_code" : "ipriceUberPH",
		"description" : "Enjoy P60 OFF on first 3 rides",
		"url": "https://iprice.ph/coupons/uber/?_id=2596631c53ca62bf2f0b93f09a1f9057def9da37&position=1&sub_product=coupon-store&_exit=%2Fcoupons%2Fuber%2F",
		"img": "image/uber.jpg",
		"type" : "popup"
   },
   {
		"title": "KKday",
		"highlight" : "5% OFF",
		"coupon_code" : "KKDAYUNIONBANK5",
		"description" : "5% off on best activities with Union Bank",
		"url": "https://iprice.ph/coupons/kkday/?_id=d6b96209997866babb641bf529fc0db44c23c733&position=3&sub_product=coupon-store&_exit=%2Fcoupons%2Fkkday%2F%3Fnocache%3D1",
		"img": "image/kkday.jpg",
		"type" : "popup"
   },
   {
		"title": "Althea",
		"highlight" : "10% OFF",
		"coupon_code" : "IPRIPH17Q4",
		"description" : "10% off sitewide with ANY purchase (limit to 3x per customer)",
		"url": "https://iprice.ph/coupons/althea/?_id=bdfeece440b308ec35d7a447cfeb86793b30a3e7&position=4&sub_product=coupon-store&_exit=%2Fcoupons%2Falthea%2F",
		"img": "image/althea.jpg",
		"type" : "popup"
   },
   {
		"title": "Lazada",
		"highlight" : "8% OFF",
		"coupon_code" : "IPRICE8",
		"description" : "8% off when you spend P1,000 and above",
		"url": "https://iprice.ph/coupons/lazada/?_id=2d56adb451663623e38e2825bfb17af08d843ae9&position=2&sub_product=coupon-store&_exit=%2Fcoupons%2Flazada%2F%3Fnocache%3D1",
		"img": "image/lazada.jpg",
		"type" : "popup"
   },
   {
		"title": "Uber",
		"highlight" : "P60 OFF",
		"coupon_code" : "IPRICEPH2017",
		"description" : "Enjoy P60 off on first 3 Uber rides",
		"url": "https://iprice.ph/coupons/uber/?_id=b88377bb8cedf34e5b84d521eb6f45d64df7a4aa&position=2&sub_product=coupon-store&_exit=%2Fcoupons%2Fuber%2F%3Fnocache%3D1",
		"img": "image/uber.jpg",
		"type" : "popup"
   },
   {
		"title": "Klook",
		"highlight" : "75% OFF",
		"coupon_code" : "KLKDBSHK",
		"description" : "Up to 75% Off on selected travel activities with DBS HK cards",
		"url": "https://iprice.ph/coupons/klook/?_id=5debcabdf68427c9a5cd46d91989e52166538d11&position=1&sub_product=coupon-store&_exit=%2Fcoupons%2Fklook%2F",
		"img": "image/klook.jpg",
		"type" : "popup"
   },
   {
		"title": "Watchportal",
		"highlight" : "5% OFF",
		"coupon_code" : "IPRICE5%",
		"description" : "Extra 5% off on best selling watches",
		"url": "https://iprice.ph/coupons/watchportal/?_id=2a6d47d22d4b9ef6385c920168871bc1841777bb&position=8&sub_product=coupon-store&_exit=%2Fcoupons%2Fwatchportal%2F",
		"img": "image/watchportal.jpg",
		"type" : "popup"
   }
 ],
"stores" : [
	   {
			"title": "Zalora",
			"url": "https://iprice.ph/coupons/zalora/?utm_source=onsite&utm_medium=landing_page&utm_campaign=11_11_Sale",
			"img": "image/zalora.jpg"
	   },
	   {
	   		"title": "Lazada",
	   		"url" : "https://iprice.ph/coupons/lazada/?utm_source=onsite&utm_medium=landing_page&utm_campaign=11_11_Sale",
	   		"img": "image/lazada.jpg"
	   },
	   {
	   		"title": "Agoda",
	   		"url" : "https://iprice.ph/coupons/agoda/?utm_source=onsite&utm_medium=landing_page&utm_campaign=11_11_Sale",
	   		"img": "image/agoda.jpg"
	   },
	   {
	   		"title": "Expedia",
	   		"url" : "https://iprice.ph/coupons/expedia/?utm_source=onsite&utm_medium=landing_page&utm_campaign=11_11_Sale",
	   		"img": "image/expedia.jpg"
	   },
	   {
	   		"title": "Hotels.com",
	   		"url" : "https://iprice.ph/coupons/hotelscom/?utm_source=onsite&utm_medium=landing_page&utm_campaign=11_11_Sale",
	   		"img": "image/hotelscom.jpg"
	   },
	   {
	   		"title": "Althea",
	   		"url" : "https://iprice.ph/coupons/althea/?utm_source=onsite&utm_medium=landing_page&utm_campaign=11_11_Sale",
	   		"img": "image/althea.jpg"
	   },
	   {
	   		"title": "Shopee",
	   		"url" : "https://iprice.ph/coupons/shopee/?utm_source=onsite&utm_medium=landing_page&utm_campaign=11_11_Sale",
	   		"img": "image/shopee.jpg"
	   },
	   {
	   		"title": "Airbnb",
	   		"url" : "https://iprice.ph/coupons/airbnb/?utm_source=onsite&utm_medium=landing_page&utm_campaign=11_11_Sale",
	   		"img": "image/airbnb.jpg"
	   }
]	
}
