{
 "products" : [
 	{
		"title": "Taobao",
		"description" : "Taobao 1111 Sale",
		"url": "http://bit.ly/2h9Pfdo",
		"img": "image/taobao_banner.jpg"
	},
	{
		"title": "Philips Lazada",
		"description" : "Philips Lazada 1111 Sale",
		"url": "http://bit.ly/2zjnE4e",
		"img": "image/philips_lazada_banner.jpg"
	},
	{
		"title": "Health & Beauty Lazada",
		"description" : "Health & Beauty Lazada 1111 Sale",
		"url": "http://bit.ly/2zjnslw",
		"img": "image/health_beauty_banner.jpg"
	}
 ],
 "top_brands": [
	   {
			"title": "Puma",
			"url": "https://iprice.sg/puma/?utm_source=onsite&utm_medium=landing_page&utm_campaign=11_11_Sale",
			"img": "image/puma-sq.jpg"
	   },
	   {
	   		"title": "Garmin",
	   		"url" : "https://iprice.sg/garmin/?utm_source=onsite&utm_medium=landing_page&utm_campaign=11_11_Sale",
	   		"img": "image/garmin-sq.jpg"
	   },
	   {
	   		"title": "MCM",
	   		"url" : "https://iprice.sg/mcm/?utm_source=onsite&utm_medium=landing_page&utm_campaign=11_11_Sale",
	   		"img": "image/mcm-sq.jpg"
	   },
	   {
	   		"title": "Adidas",
	   		"url" : "https://iprice.sg/adidas/?utm_source=onsite&utm_medium=landing_page&utm_campaign=11_11_Sale",
	   		"img": "image/adidas-sq.jpg"
	   },
	   {
	   		"title": "Vans",
	   		"url" : "https://iprice.sg/vans/?utm_source=onsite&utm_medium=landing_page&utm_campaign=11_11_Sale",
	   		"img": "image/vans-sq.jpg"
	   },
	   {
	   		"title": "Seiko",
	   		"url" : "https://iprice.sg/seiko/?utm_source=onsite&utm_medium=landing_page&utm_campaign=11_11_Sale",
	   		"img": "image/seiko-sq.jpg"
	   }
	],
 "brands": [
        {
            "title": "Gearbest",
            "description": "Gearbest 1111 Sale",
            "url": "http://bit.ly/2hhZzUo",
            "img": "image/Gearbestbox_banner_mini.jpg",
            "cta" : "Shop Now"
        },
        {
            "title": "Uber",
            "description": "For no reason being late again",
            "url": "https://iprice.sg/coupons/uber/?utm_source=onsite&utm_medium=landing_page&utm_campaign=11_11_Sale",
            "img": "image/Uber_box_banner.jpg",
            "cta" : "Shop Now"
        },
        {
            "title": "Zalora",
            "description": "11.11 Singles Day Your Way. Up to 50% Off",
            "url": "http://bit.ly/2xNha9U",
            "img": "image/zalora_square_50.jpg",
            "cta" : "Shop Now"
        },
        {
            "title": "Yoox",
            "description": "",
            "url": "http://bit.ly/2yfxfoQ",
            "img": "image/Yoox_banner_square.jpg"
        }
    ],
 "coupons": [
   {
		"title": "Zalora",
		"highlight" : "Discount up to 30%",
		"coupon_code" : "IPRICENOV",
		"description" : "For Shoes & Bags: Get 2 for 20%, Buy 3 for 30% + EXTRA 14% OFF!",
		"url": "https://iprice.sg/coupons/zalora/?_id=f7f3b9d54e2ca846ba3d03f97c32eb56cd0acd1a&position=5&sub_product=coupon-store&_exit=%2Fcoupons%2Fzalora%2F",
		"img": "image/zalora.jpg",
		"type" : "popup"
   },
   {
		"title": "Zalora",
		"highlight" : "Discount up to 70%",
		"coupon_code" : "IPRICENOV",
		"description" : "For women, get up to 70% + 14% OFF",
		"url": "https://iprice.sg/r/c/?_id=07b0889ee5095f2eca87f6a5b46714113eefce13&position=1&sub_product=coupon-store&_exit=%2Fcoupons%2Fzalora%2F%3F_id%3D07b0889ee5095f2eca87f6a5b46714113eefce13%26position%3D1%26sub_product%3Dcoupon-store%26_exit%3D%252Fcoupons%252Fzalora%252F%253Fnocache%253D1",
		"img": "image/zalora.jpg",
		"type" : "popup"
   },
   {
		"title": "Zalora",
		"highlight" : "Discount up to 50%",
		"coupon_code" : "IPRICENOV",
		"description" : "Shop dresses, receive up to 50% + 14% off!",
		"url": "https://iprice.sg/r/c/?_id=a586753edb56dcf15dbb7da39524d23873c3a072&position=2&sub_product=coupon-store&_exit=%2Fcoupons%2Fzalora%2F%3F_id%3D07b0889ee5095f2eca87f6a5b46714113eefce13%26position%3D1%26sub_product%3Dcoupon-store%26_exit%3D%252Fcoupons%252Fzalora%252F%253F_id%253D07b0889ee5095f2eca87f6a5b46714113eefce13%2526position%253D1%2526sub_product%253Dcoupon-store%2526_exit%253D%25252Fcoupons%25252Fzalora%25252F%25253Fnocache%25253D1",
		"img": "image/zalora.jpg",
		"type" : "popup"
   },
   {
		"title": "Zalora",
		"highlight" : "Discount up to 70%",
		"coupon_code" : "IPRICENOV",
		"description" : "Get up to 70% + 14% OFF for Zalora Labels Men!",
		"url": "https://iprice.sg/coupons/zalora/?_id=56d3ae25637586ea37210be8e2f89621964fd85c&position=2&sub_product=coupon-store&_exit=%2Fcoupons%2Fzalora%2F",
		"img": "image/zalora.jpg",
		"type" : "popup"
   },
   {
		"title": "Zalora",
		"highlight" : "18% OFF",
		"coupon_code" : "OCTPAYDAY",
		"description" : "Get 18% OFF Storewide!",
		"url": "https://iprice.sg/coupons/zalora/?_id=e42a838c68ecf1b4c28798a3437ad8dad2560c67&position=1&sub_product=coupon-store&_exit=%2Fcoupons%2Fzalora%2F",
		"img": "image/zalora.jpg",
		"type" : "popup"
   },
   {
		"title": "Zalora",
		"highlight" : "Up to 30% OFF",
		"coupon_code" : "IPRICENOV",
		"description" : "For Shoes & Bags: Get 2 for 20%, Buy 3 for 30% + EXTRA 14% OFF!",
		"url": "https://iprice.sg/coupons/zalora/?_id=f7f3b9d54e2ca846ba3d03f97c32eb56cd0acd1a&position=5&sub_product=coupon-store&_exit=%2Fcoupons%2Fzalora%2F",
		"img": "image/zalora.jpg",
		"type" : "popup"
   },
   {
		"title": "Zalora",
		"highlight" : "14% OFF",
		"coupon_code" : "IPRICENOV",
		"description" : "Get 14% OFF Storewide with Min Spend SG$120",
		"url": "https://iprice.sg/coupons/zalora/?_id=d89fe52895e0616b4bd001354401510a2afa84f1&position=1&sub_product=coupon-store&_exit=%2Fcoupons%2Fzalora%2F%3F_id%3Dd89fe52895e0616b4bd001354401510a2afa84f1%26position%3D1%26sub_product%3Dcoupon-store%26_exit%3D%252Fcoupons%252Fzalora%252F%253Fnocache%253D1",
		"img": "image/zalora.jpg",
		"type" : "popup"
   },
   {
		"title": "Lazada",
		"highlight" : "$7 OFF",
		"coupon_code" : "WATSONS7",
		"description" : "Watsons Sale: Get SG$7 OFF When Buy Any Products!",
		"url": "https://iprice.sg/coupons/lazada/?_id=4f698bdd9627e8eea0bfacb1bd2f4514520b310a&position=7&sub_product=coupon-store&_exit=%2Fcoupons%2Flazada%2F%3F_id%3D385984f9e2e732cb45ab1b18acf44f5b42ed48c4%26position%3D4%26sub_product%3Dcoupon-store%26_exit%3D%252Fcoupons%252Flazada%252F%253F_id%253D385984f9e2e732cb45ab1b18acf44f5b42ed48c4%2526position%253D4%2526sub_product%253Dcoupon-store%2526_exit%253D%25252Fcoupons%25252Flazada%25252F%25253F_id%25253D3880825afa0e96733b647b81e6db62e1d24bd9bb%252526position%25253D3%252526sub_product%25253Dcoupon-store%252526_exit%25253D%2525252Fcoupons%2525252Flazada%2525252F",
		"img": "image/lazada.jpg",
		"type" : "popup"
   },
   {
		"title": "Lazada",
		"highlight" : "$120 OFF",
		"coupon_code" : "LNV11120",
		"description" : "Get SG$120 OFF for Lenovo Products. Apply Lazada Coupon!",
		"url": "https://iprice.sg/coupons/lazada/?_id=6e950a08791973efa324f7432640569944aa6881&position=5&sub_product=coupon-store&_exit=%2Fcoupons%2Flazada%2F%3F_id%3D6e950a08791973efa324f7432640569944aa6881%26position%3D5%26sub_product%3Dcoupon-store%26_exit%3D%252Fcoupons%252Flazada%252F%253F_id%253D4f698bdd9627e8eea0bfacb1bd2f4514520b310a%2526position%253D7%2526sub_product%253Dcoupon-store%2526_exit%253D%25252Fcoupons%25252Flazada%25252F%25253F_id%25253D385984f9e2e732cb45ab1b18acf44f5b42ed48c4%252526position%25253D4%252526sub_product%25253Dcoupon-store%252526_exit%25253D%2525252Fcoupons%2525252Flazada%2525252F%2525253F_id%2525253D385984f9e2e732cb45ab1b18acf44f5b42ed48c4%25252526position%2525253D4%25252526sub_product%2525253Dcoupon-store%25252526_exit%2525253D%252525252Fcoupons%252525252Flazada%252525252F%252525253F_id%252525253D3880825afa0e96733b647b81e6db62e1d24bd9bb%2525252526position%252525253D3%2525252526sub_product%252525253Dcoupon-store%2525252526_exit%252525253D%25252525252Fcoupons%25252525252Flazada%25252525252F",
		"img": "image/lazada.jpg",
		"type" : "popup"
   },
   {
		"title": "Lazada",
		"highlight" : "Up to 20%",
		"coupon_code" : "TEFAL1111",
		"description" : "Lazada Voucher Code: Buy Tefal Products, Get 20% OFF!",
		"url": "https://iprice.sg/coupons/lazada/?_id=3880825afa0e96733b647b81e6db62e1d24bd9bb&position=3&sub_product=coupon-store&_exit=%2Fcoupons%2Flazada%2F",
		"img": "image/lazada.jpg",
		"type" : "popup"
   },
   {
		"title": "Lazada",
		"highlight" : "Up to 50%",
		"coupon_code" : "LADAPP10",
		"description" : "Download App, Get up to 50% OFF Storewide",
		"url": "https://iprice.sg/coupons/lazada/?_id=a28b75e31aaff7952194f7d2dc5a40a813f794df&position=1&sub_product=coupon-store&_exit=%2Fcoupons%2Flazada%2F",
		"img": "image/lazada.jpg",
		"type" : "popup"
   },
   {
		"title": "Lazada",
		"highlight" : "$6 OFF",
		"coupon_code" : "*****",
		"description" : "Receive $6 OFF express deals with your Citibank Card",
		"url": "https://iprice.sg/coupons/lazada/?_id=535abd3e13c5df78e80e82a2a563787f942003cb&position=13&sub_product=coupon-store&_exit=%2Fcoupons%2Flazada%2F",
		"img": "image/lazada.jpg",
		"type" : "popup"
   },
   {
		"title": "Lazada",
		"highlight" : "$200 OFF",
		"coupon_code" : "AC11200",
		"description" : "Lazada 11.11 Sale: Buy Acer, Get SG$200 OFF, Min Purchase SG$2500!",
		"url": "https://iprice.sg/coupons/lazada/?_id=c58a497c7a7014510e35f72e23be24c5cd2ff63b&position=3&sub_product=coupon-store&_exit=%2Fcoupons%2Flazada%2F%3F_id%3Dc58a497c7a7014510e35f72e23be24c5cd2ff63b%26position%3D3%26sub_product%3Dcoupon-store%26_exit%3D%252Fcoupons%252Flazada%252F",
		"img": "image/lazada.jpg",
		"type" : "popup"
   },
   {
		"title": "Lazada",
		"highlight" : "$11 OFF",
		"coupon_code" : "LOVERB11",
		"description" : "Buy Reckitt Benckiser Products, Enjoy SG$11 OFF Min Spend SG$50",
		"url": "https://iprice.sg/coupons/lazada/?_id=d859e9b1de9c18e6d6ca31a14ee7834ca225e8d8&position=4&sub_product=coupon-store&_exit=%2Fcoupons%2Flazada%2F%3F_id%3Dc58a497c7a7014510e35f72e23be24c5cd2ff63b%26position%3D3%26sub_product%3Dcoupon-store%26_exit%3D%252Fcoupons%252Flazada%252F%253F_id%253Dc58a497c7a7014510e35f72e23be24c5cd2ff63b%2526position%253D3%2526sub_product%253Dcoupon-store%2526_exit%253D%25252Fcoupons%25252Flazada%25252F",
		"img": "image/lazada.jpg",
		"type" : "popup"
   },
   {
		"title": "Lazada",
		"highlight" : "18% OFF",
		"coupon_code" : "ORIPRICE2017",
		"description" : "Enjoy 18% off storewide for new customers!",
		"url": "https://iprice.sg/coupons/lazada/?_id=51ffbb81d993330dc87a1c8a79d91e98185bdea5&position=1&sub_product=coupon-store&_exit=%2Fcoupons%2Flazada%2F",
		"img": "image/lazada.jpg",
		"type" : "popup"
   },
   {
		"title": "Microsoft",
		"highlight" : "$249 OFF",
		"coupon_code" : "required",
		"description" : "Save $249 on Surface 3",
		"url": "https://iprice.sg/r/c/?_id=d6c8d019b5be9ae93e15e674eeae1cde8078370b&position=7&sub_product=coupon-store&_exit=%2Fcoupons%2Fmicrosoft%2F",
		"img": "image/microsoft.jpg",
		"type" : "direct"
   },
   {
		"title": "Qoo10",
		"highlight" : "$110 OFF",
		"coupon_code" : "Q10SG110",
		"description" : "Enjoy SG$110 OFF, Min Spend SG$800 for Selected Items!",
		"url": "https://iprice.sg/coupons/qoo10/?_id=b34767a0526ca9a61e59fe03557c9ed616e127a5&position=1&sub_product=coupon-store&_exit=%2Fcoupons%2Fqoo10%2F%3Fnocache%3D1",
		"img": "image/qoo10.jpg",
		"type" : "popup"
   },
   {
		"title": "Qoo10",
		"highlight" : "$30 OFF",
		"coupon_code" : "Q10SG30",
		"description" : "Get SG$30 OFF, Min Spend SG$200",
		"url": "https://iprice.sg/coupons/qoo10/?_id=94a93b9337b046ff44eddd295a289cb3ae502814&position=2&sub_product=coupon-store&_exit=%2Fcoupons%2Fqoo10%2F%3F_id%3Db34767a0526ca9a61e59fe03557c9ed616e127a5%26position%3D1%26sub_product%3Dcoupon-store%26_exit%3D%252Fcoupons%252Fqoo10%252F%253Fnocache%253D1",
		"img": "image/qoo10.jpg",
		"type" : "popup"
   },
   {
		"title": "Qoo10",
		"highlight" : "$11 OFF",
		"coupon_code" : "Q10SG11",
		"description" : "Receive SG$11 OFF, Min Spend SG$50 for Selected Items!",
		"url": "https://iprice.sg/coupons/qoo10/?_id=162a9706dcdbfa968b50d6454287968d99ae7d3e&position=3&sub_product=coupon-store&_exit=%2Fcoupons%2Fqoo10%2F%3F_id%3D162a9706dcdbfa968b50d6454287968d99ae7d3e%26position%3D3%26sub_product%3Dcoupon-store%26_exit%3D%252Fcoupons%252Fqoo10%252F%253F_id%253D94a93b9337b046ff44eddd295a289cb3ae502814%2526position%253D2%2526sub_product%253Dcoupon-store%2526_exit%253D%25252Fcoupons%25252Fqoo10%25252F%25253F_id%25253Db34767a0526ca9a61e59fe03557c9ed616e127a5%252526position%25253D1%252526sub_product%25253Dcoupon-store%252526_exit%25253D%2525252Fcoupons%2525252Fqoo10%2525252F%2525253Fnocache%2525253D1",
		"img": "image/qoo10.jpg",
		"type" : "popup"
   },
   {
		"title": "Qoo10",
		"highlight" : "$20 OFF",
		"coupon_code" : "Q10SGMP20",
		"description" : "For Masterpass Users: Enjoy SG$20 OFF by Spending Minimum SG$40!",
		"url": "https://iprice.sg/coupons/qoo10/?_id=2ee811502104c5327ac51140c3768e24d64ea44f&position=4&sub_product=coupon-store&_exit=%2Fcoupons%2Fqoo10%2F%3F_id%3D162a9706dcdbfa968b50d6454287968d99ae7d3e%26position%3D3%26sub_product%3Dcoupon-store%26_exit%3D%252Fcoupons%252Fqoo10%252F%253F_id%253D162a9706dcdbfa968b50d6454287968d99ae7d3e%2526position%253D3%2526sub_product%253Dcoupon-store%2526_exit%253D%25252Fcoupons%25252Fqoo10%25252F%25253F_id%25253D94a93b9337b046ff44eddd295a289cb3ae502814%252526position%25253D2%252526sub_product%25253Dcoupon-store%252526_exit%25253D%2525252Fcoupons%2525252Fqoo10%2525252F%2525253F_id%2525253Db34767a0526ca9a61e59fe03557c9ed616e127a5%25252526position%2525253D1%25252526sub_product%2525253Dcoupon-store%25252526_exit%2525253D%252525252Fcoupons%252525252Fqoo10%252525252F%252525253Fnocache%252525253D1",
		"img": "image/qoo10.jpg",
		"type" : "popup"
   },
   {
		"title": "Qoo10",
		"highlight" : "$11 OFF",
		"coupon_code" : "Q10SGMC11",
		"description" : "For Mastercard Users: Get SG$11 OFF, Min Spend SG$30",
		"url": "https://iprice.sg/coupons/qoo10/?_id=65cde3b781fd63e82240f01d1a1b92945e4751a4&position=5&sub_product=coupon-store&_exit=%2Fcoupons%2Fqoo10%2F%3F_id%3D2ee811502104c5327ac51140c3768e24d64ea44f%26position%3D4%26sub_product%3Dcoupon-store%26_exit%3D%252Fcoupons%252Fqoo10%252F%253F_id%253D162a9706dcdbfa968b50d6454287968d99ae7d3e%2526position%253D3%2526sub_product%253Dcoupon-store%2526_exit%253D%25252Fcoupons%25252Fqoo10%25252F%25253F_id%25253D162a9706dcdbfa968b50d6454287968d99ae7d3e%252526position%25253D3%252526sub_product%25253Dcoupon-store%252526_exit%25253D%2525252Fcoupons%2525252Fqoo10%2525252F%2525253F_id%2525253D94a93b9337b046ff44eddd295a289cb3ae502814%25252526position%2525253D2%25252526sub_product%2525253Dcoupon-store%25252526_exit%2525253D%252525252Fcoupons%252525252Fqoo10%252525252F%252525253F_id%252525253Db34767a0526ca9a61e59fe03557c9ed616e127a5%2525252526position%252525253D1%2525252526sub_product%252525253Dcoupon-store%2525252526_exit%252525253D%25252525252Fcoupons%25252525252Fqoo10%25252525252F%25252525253Fnocache%25252525253D1",
		"img": "image/qoo10.jpg",
		"type" : "popup"
   },
   {
		"title": "Qoo10",
		"highlight" : "10% OFF",
		"coupon_code" : "QOO10SG",
		"description" : "Get 10% OFF Storewide!",
		"url": "https://iprice.sg/coupons/qoo10/?_id=a7ec2d73a5204a7cf5fc46e5404d35e9de95c6c5&position=1&sub_product=coupon-store&_exit=%2Fcoupons%2Fqoo10%2F%3Fnocache%3D1",
		"img": "image/qoo10.jpg",
		"type" : "popup"
   },
   {
		"title": "YOOX",
		"highlight" : "Free Shipping",
		"coupon_code" : "IPRICEFS",
		"description" : "Enjoy free shipping with no min purchase",
		"url": "https://iprice.sg/coupons/yoox/?_id=eae2871c5236f3ddafd196c73614cca9508b2fa2&position=1&sub_product=coupon-store&_exit=%2Fcoupons%2Fyoox%2F",
		"img": "image/yoox.jpg",
		"type" : "popup"
   },
   {
		"title": "SmartBuyGlasses",
		"highlight" : "10% OFF",
		"coupon_code" : "IPRICE10",
		"description" : "Get 10% OFF Storewide!",
		"url": "https://iprice.sg/coupons/smartbuyglasses/?_id=829f763912bf5bf64623de9edc58ca344ab98ba1&position=1&sub_product=coupon-store&_exit=%2Fcoupons%2Fsmartbuyglasses%2F%3F_id%3D829f763912bf5bf64623de9edc58ca344ab98ba1%26position%3D1%26sub_product%3Dcoupon-store%26_exit%3D%252Fcoupons%252Fsmartbuyglasses%252F",
		"img": "image/smartbuyglasses.jpg",
		"type" : "popup"
   },
   {
		"title": "KKDay",
		"highlight" : "20% OFF",
		"coupon_code" : "IPRICE20",
		"description" : "Book Selected Activities, Receive 20% OFF!",
		"url": "https://iprice.sg/coupons/kkday/?_id=18a69cace11b55997ee5cb6794c5be5baf751af1&position=1&sub_product=coupon-store&_exit=%2Fcoupons%2Fkkday%2F",
		"img": "image/kkday.jpg",
		"type" : "popup"
   },
   {
		"title": "Althea",
		"highlight" : "11% OFF",
		"coupon_code" : "IPRI1111SG17",
		"description" : "Get 11% OFF Storewide!",
		"url": "https://iprice.sg/coupons/althea/?_id=e821dcb313363cf77cc0b2f07f9e3d4f4fec4127&position=1&sub_product=coupon-store&_exit=%2Fcoupons%2Falthea%2F%3F_id%3Df7b5b787b1b8b516f283353b6af77687b7c48871%26position%3D2%26sub_product%3Dcoupon-store%26_exit%3D%252Fcoupons%252Falthea%252F",
		"img": "image/althea.jpg",
		"type" : "popup"
   },
   {
		"title": "Klook",
		"highlight" : "$100 OFF",
		"coupon_code" : "YES100",
		"description" : "Book Year End Holiday, GET $100 OFF!",
		"url": "https://iprice.sg/coupons/klook/?_id=da4b9237bacccdf19c0760cab7aec4a8359010b0&position=1&sub_product=coupon-store&_exit=%2Fcoupons%2Fklook%2F",
		"img": "image/klook.jpg",
		"type" : "popup"
   },
   {
		"title": "Zuji",
		"highlight" : "12% OFF",
		"coupon_code" : "*****",
		"description" : "Get 12% OFF for hotels using MasterCard",
		"url": "https://iprice.sg/coupons/zuji/?_id=a3b9da402170a8b7ef8aeed88d61db0bd2f5612e&position=1&sub_product=coupon-store&_exit=%2Fcoupons%2Fzuji%2F",
		"img": "image/zuji.jpg",
		"type" : "popup"
   },
   {
		"title": "Honestbee",
		"highlight" : "$20 OFF",
		"coupon_code" : "*****",
		"description" : "Get SG$20 discount with min. spend of SG$85 by using Standard Chartered Card",
		"url": "https://iprice.sg/coupons/honestbee/?_id=422fe34445487e336c6a440899e320b9a8c92cae&position=13&sub_product=coupon-store&_exit=%2Fcoupons%2Fhonestbee%2F",
		"img": "image/honestbee.jpg",
		"type" : "popup"
   },
   {
		"title": "Redmart",
		"highlight" : "$15 OFF",
		"coupon_code" : "15DIPRIC",
		"description" : "Enjoy SG$15 OFF storewide!",
		"url": "https://iprice.sg/coupons/redmart/?_id=2286ef1ac73a1f0991902f09630245bc49ac5344&position=1&sub_product=coupon-store&_exit=%2Fcoupons%2Fredmart%2F",
		"img": "image/redmart.jpg",
		"type" : "popup"
   },
   {
		"title": "Uber",
		"highlight" : "$11 OFF",
		"coupon_code" : "1PR1CESG",
		"description" : "Get SG$11 OFF for First Rides!",
		"url": "https://iprice.sg/coupons/uber/?_id=c9b8a504d867734e1329733cfed9d10046ea6f65&position=1&sub_product=coupon-store&_exit=%2Fcoupons%2Fuber%2F%3Fnocache%3D1",
		"img": "image/uber.jpg",
		"type" : "popup"
   },
   {
		"title": "Hotels.com",
		"highlight" : "7% OFF",
		"coupon_code" : "OMGNOV17",
		"description" : "Hotels.com 11.11 Sale: Enjoy EXTRA 7% OFF on Hotels Booking!",
		"url": "https://iprice.sg/coupons/hotelscom/?_id=5e56ab12cf30e7893cfb3ac7403844444e4a5928&position=1&sub_product=coupon-store&_exit=%2Fcoupons%2Fhotelscom%2F%3Fnocache%3D1",
		"img": "image/hotelscom.jpg",
		"type" : "popup"
   },
   {
		"title": "Charles & Keith",
		"highlight" : "50% OFF",
		"coupon_code" : "*****",
		"description" : "Charles & Keith 11.11 Sale: Get up to 50% OFF for Selected Styles!",
		"url": "https://iprice.sg/coupons/charles-keith/?_id=78da731674b8a2679704581ce2c8f4bb8d7544f1&position=1&sub_product=coupon-store&_exit=%2Fcoupons%2Fcharles-keith%2F%3Fnocache%3D1",
		"img": "image/charles-keith.jpg",
		"type" : "popup"
   },
   {
		"title": "Althea",
		"highlight" : "25% OFF",
		"coupon_code" : "WOW25",
		"description" : "Buy Selected Makeup & Skin Care, Get 25% OFF",
		"url": "https://iprice.sg/coupons/althea/?_id=4ba3e98f981902084d505bb0be441777db1495e3&position=4&sub_product=coupon-store&_exit=%2Fcoupons%2Falthea%2F%3F_id%3D0c47c784009d7f4175eba392ae63ad65474fe951%26position%3D3%26sub_product%3Dcoupon-store%26_exit%3D%252Fcoupons%252Falthea%252F",
		"img": "image/althea.jpg",
		"type" : "popup"
   },
   {
		"title": "KKday",
		"highlight" : "20% OFF",
		"coupon_code" : "IPRICE20",
		"description" : "Get 20% OFF for Citibank Users",
		"url": "https://iprice.sg/coupons/kkday/?_id=7b582ac19a6a7dacabcdd8c8beb06b1b94d30a9a&position=1&sub_product=coupon-store&_exit=%2Fcoupons%2Fkkday%2F",
		"img": "image/kkday.jpg",
		"type" : "popup"
   },
   {
		"title": "UberEATS",
		"highlight" : "$5 OFF",
		"coupon_code" : "IPRICE5",
		"description" : "Enjoy $5 off for first order!",
		"url": "https://iprice.sg/coupons/ubereats/?_id=84329c7b94c88ebe85dff0c2cdba64ad859f38da&position=1&sub_product=coupon-store&_exit=%2Fcoupons%2Fubereats%2F",
		"img": "image/ubereats.jpg",
		"type" : "popup"
   },
   {
		"title": "Redmart",
		"highlight" : "$15 OFF",
		"coupon_code" : "15DIPRIC",
		"description" : "Enjoy $15 off storewide!",
		"url": "https://iprice.sg/coupons/redmart/?_id=2286ef1ac73a1f0991902f09630245bc49ac5344&position=1&sub_product=coupon-store&_exit=%2Fcoupons%2Fredmart%2F",
		"img": "image/redmart.jpg",
		"type" : "popup"
   },
   {
		"title": "Gearbest",
		"highlight" : "10% OFF",
		"coupon_code" : "IPRICE10",
		"description" : "Get 10% off sitewide",
		"url": "https://iprice.sg/coupons/gearbest/?_id=074a3da1eff208ee28f70a7c5d2fdcb7c0739de0&position=1&sub_product=coupon-store&_exit=%2Fcoupons%2Fgearbest%2F%3Fnocache%3D1",
		"img": "image/gearbest.jpg",
		"type" : "popup"
   },
   {
		"title": "Expedia",
		"highlight" : "10% OFF",
		"coupon_code" : "JOG10OFF",
		"description" : "Get 10% off hotels in Yogyakarta!",
		"url": "https://iprice.sg/coupons/expedia/?_id=634636bb3b798c46c5815961ce54be6fb6c13570&position=2&sub_product=coupon-store&_exit=%2Fcoupons%2Fexpedia%2F%3Fnocache%3D1",
		"img": "image/expedia.jpg",
		"type" : "popup"
   },
   {
		"title": "Agoda",
		"highlight" : "10% OFF",
		"coupon_code" : "5A9GQAB",
		"description" : "Get 10% OFF for hotels in Melbourne!",
		"url": "https://iprice.sg/coupons/agoda/?_id=40c140de31b3b7deb7093fe8f4a0fb7c26d89a4f&position=3&sub_product=coupon-store&_exit=%2Fcoupons%2Fagoda%2F",
		"img": "image/agoda.jpg",
		"type" : "popup"
   },
   {
		"title": "Sephora",
		"highlight" : "Free Gift",
		"coupon_code" : "CHARMED",
		"description" : "Spend min. SG$250 and receive exclusive cardholder and 4 key chains for Gold & Black Members",
		"url": "https://iprice.sg/coupons/sephora/?_id=b852ee9c9a946c3ace1e83f0e8abd3474c19dac4&position=2&sub_product=coupon-store&_exit=%2Fcoupons%2Fsephora%2F%3Fnocache%3D1",
		"img": "image/sephora.jpg",
		"type" : "popup"
   }
 ],
"stores" : [
	   {
			"title": "Zalora",
			"url": "https://iprice.sg/coupons/zalora/?utm_source=onsite&utm_medium=landing_page&utm_campaign=11_11_Sale",
			"img": "image/zalora.jpg"
	   },
	   {
	   		"title": "Lazada",
	   		"url" : "https://iprice.sg/coupons/lazada/?utm_source=onsite&utm_medium=landing_page&utm_campaign=11_11_Sale",
	   		"img": "image/lazada.jpg"
	   },
	   {
	   		"title": "Agoda",
	   		"url" : "https://iprice.sg/coupons/agoda/?utm_source=onsite&utm_medium=landing_page&utm_campaign=11_11_Sale",
	   		"img": "image/agoda.jpg"
	   },
	   {
	   		"title": "Expedia",
	   		"url" : "https://iprice.sg/coupons/expedia/?utm_source=onsite&utm_medium=landing_page&utm_campaign=11_11_Sale",
	   		"img": "image/expedia.jpg"
	   },
	   {
	   		"title": "Hotels.com",
	   		"url" : "https://iprice.sg/coupons/hotelscom/?utm_source=onsite&utm_medium=landing_page&utm_campaign=11_11_Sale",
	   		"img": "image/hotelscom.jpg"
	   },
	   {
	   		"title": "UberEATS",
	   		"url" : "https://iprice.sg/coupons/ubereats/?utm_source=onsite&utm_medium=landing_page&utm_campaign=11_11_Sale",
	   		"img": "image/ubereats.jpg"
	   },
	   {
	   		"title": "Redmart",
	   		"url" : "https://iprice.sg/coupons/redmart/?utm_source=onsite&utm_medium=landing_page&utm_campaign=11_11_Sale",
	   		"img": "image/redmart.jpg"
	   },
	   {
	   		"title": "Uber",
	   		"url" : "https://iprice.sg/coupons/uber/?utm_source=onsite&utm_medium=landing_page&utm_campaign=11_11_Sale",
	   		"img": "image/uber.jpg"
	   }
]	
}
