{
 "products" : [],
 "top_brands": [
	   {
			"title": "Onitsuka Tiger",
			"url": "https://ipricethailand.com/onitsuka-tiger/?utm_source=onsite&utm_medium=landing_page&utm_campaign=11_11_Sale",
			"img": "image/onitsukatiger-sq.jpg"
	   },
	   {
	   		"title": "Converse",
	   		"url" : "https://ipricethailand.com/converse/?utm_source=onsite&utm_medium=landing_page&utm_campaign=11_11_Sale",
	   		"img": "image/converse-sq.jpg"
	   },
	   {
	   		"title": "Adidas",
	   		"url" : "https://ipricethailand.com/adidas/?utm_source=onsite&utm_medium=landing_page&utm_campaign=11_11_Sale",
	   		"img": "image/adidas-sq.jpg"
	   },
	   {
	   		"title": "Lacoste",
	   		"url" : "https://ipricethailand.com/lacoste/?utm_source=onsite&utm_medium=landing_page&utm_campaign=11_11_Sale",
	   		"img": "image/lacoste-sq.jpg"
	   },
	   {
	   		"title": "Innisfree",
	   		"url" : "https://ipricethailand.com/innisfree/?utm_source=onsite&utm_medium=landing_page&utm_campaign=11_11_Sale",
	   		"img": "image/innisfree-sq.jpg"
	   },
	   {
	   		"title": "Nike",
	   		"url" : "https://ipricethailand.com/nike/?utm_source=onsite&utm_medium=landing_page&utm_campaign=11_11_Sale",
	   		"img": "image/nike-sq.jpg"
	   }
	],
 "brands": [
        {
            "title": "Looksi",
            "description": "ได้เวลาเปลี่ยนมือถือและช้อปอุปกรณ์ชิ้นใหม่ด้วยโปรแรงลดกระหน่ำ",
            "url": "http://bit.ly/2ziPcqi",
            "img": "image/looksi-1111-sale-1_mini.jpg",
            "cta" : "ช้อปเลย"
        },
        {
            "title": "รองเท้า",
            "description": "เสริมลุคให้ดีขึ้นด้วยรองเท้าคู่โดนใจที่เป็นเจ้าของได้ในราคาสุดสบายกระเป๋า",
            "url": "https://ipricethailand.com/รองเทา/?utm_source=onsite&utm_medium=landing_page&utm_campaign=11_11_Sale",
            "img": "image/shoes.jpg",
            "cta" : "ช้อปเลย",
            "default" : true
        },
        {
            "title": "Officemate",
            "description": "จะใบนี้ใบไหนก็ถูกใจ แล้วจะดีกว่าไหมถ้าซื้อกระเป๋าใบใหม่ในราคาที่ถูกกว่า",
            "url": "http://bit.ly/2hepc8y",
            "img": "image/officemate-111-sale-3_mini.jpg",
            "cta" : "ช้อปเลย"
        },
        {
            "title": "Lazada",
            "description": "lazada 1111 Sale",
            "url": "http://bit.ly/2hM2amC",
            "img": "image/lazadaBox_banner.png",
            "cta" : "ช้อปเลย"
        }
    ],
 "coupons": [
   {
		"title": "Konvy",
		"highlight" : "10% OFF",
		"coupon_code" : "KVKBANK150",
		"description" : "ส่วนลด 150 ฿ สิทธิพิเศษจากบัตร Kbank และได้รับเครดิตคืนเงิน 10% เมื่อช้อปสินค้าจาก Konvy",
		"url": "https://ipricethailand.com/coupons/konvy/?_id=52a87adf11cbcc10a9f5f0e53d3823aa96cf05e1&position=1&sub_product=coupon-store&_exit=%2Fcoupons%2Fkonvy%2F%3F_id%3D52a87adf11cbcc10a9f5f0e53d3823aa96cf05e1%26position%3D1%26sub_product%3Dcoupon-store%26_exit%3D%252Fcoupons%252Fkonvy%252F",
		"img": "image/konvy.jpg",
		"type" : "popup"
   },
   {
		"title": "Tops",
		"highlight" : "150 บาท",
		"coupon_code" : "required",
		"description" : "โปรโมชั่น Tops Shop Online: สมาชิก AIS รับ 150 บาทฟรี! เมื่อช้อปครบ 2,000 บาทขึ้นไป",
		"url": "https://ipricethailand.com/r/c/?_id=39f94ccff2360401119130aa1ee50f74f2ef4a59&position=1&sub_product=coupon-store&_exit=%2Fcoupons%2Ftops-shop-online%2F",
		"img": "image/tops.jpg",
		"type" : "direct"
   },
   {
		"title": "Sephora",
		"highlight" : "Canvas Pouch",
		"coupon_code" : "*****",
		"description" : "เฉพาะผู้ถือบัตร Visa ฟรีกระเป๋า Canvas Pouch เมื่อช้อปออนไลน์ที่ Sephora Thailand!",
		"url": "https://ipricethailand.com/coupons/sephora/?_id=6bd9bf11d8383ca7ab20ed06269f7d504c4d541d&position=1&sub_product=coupon-store&_exit=%2Fcoupons%2Fsephora%2F",
		"img": "image/sephora.jpg",
		"type" : "popup"
   },
   {
		"title": "AirAsiaGo",
		"highlight" : "10% OFF",
		"coupon_code" : "รับคูปองที่ร้านค้าเท่านั้น",
		"description" : "บินปลายปี ทุกเส้นทาง ในประเทศ เริ่มต้น 599 บาท! จองผ่านแอพ AirAsiaGo ลดเพิ่ม 10%!",
		"url": "https://ipricethailand.com/coupons/airasiago/?_id=5c9e92b5acc54ab7a064e28c7b2bd7e8c8f2fab8&position=1&sub_product=coupon-store&_exit=%2Fcoupons%2Fairasiago%2F",
		"img": "image/airasiago.jpg",
		"type" : "popup"
   }
 ],
"stores" : [
	   {
			"title": "Central",
			"url": "https://ipricethailand.com/coupons/central-online/?utm_source=onsite&utm_medium=landing_page&utm_campaign=11_11_Sale",
			"img": "image/central.jpg"
	   },
	   {
	   		"title": "Lazada",
	   		"url" : "https://ipricethailand.com/coupons/lazada/?utm_source=onsite&utm_medium=landing_page&utm_campaign=11_11_Sale",
	   		"img": "image/lazada.jpg"
	   },
	   {
	   		"title": "Looksi",
	   		"url" : "https://ipricethailand.com/coupons/looksi/?utm_source=onsite&utm_medium=landing_page&utm_campaign=11_11_Sale",
	   		"img": "image/looksi.jpg"
	   },
	   {
	   		"title": "Tops",
	   		"url" : "https://ipricethailand.com/coupons/tops-shop-online/?utm_source=onsite&utm_medium=landing_page&utm_campaign=11_11_Sale",
	   		"img": "image/tops.jpg"
	   },
	   {
	   		"title": "BigC",
	   		"url" : "https://ipricethailand.com/coupons/big-c-online/?utm_source=onsite&utm_medium=landing_page&utm_campaign=11_11_Sale",
	   		"img": "image/big-c.jpg"
	   },
	   {
	   		"title": "Konvy",
	   		"url" : "https://ipricethailand.com/coupons/konvy/?utm_source=onsite&utm_medium=landing_page&utm_campaign=11_11_Sale",
	   		"img": "image/konvy.jpg"
	   },
	   {
	   		"title": "Shopat24",
	   		"url" : "https://ipricethailand.com/coupons/shopat24/?utm_source=onsite&utm_medium=landing_page&utm_campaign=11_11_Sale",
	   		"img": "image/shopat24.jpg"
	   },
	   {
	   		"title": "Uber",
	   		"url" : "https://ipricethailand.com/coupons/uber/?utm_source=onsite&utm_medium=landing_page&utm_campaign=11_11_Sale",
	   		"img": "image/uber.jpg"
	   }
]	
}
